Metadata-Version: 2.2
Name: hello-py-2024
Version: 0.0.1
Summary: Junjie's private utils.
Home-page: https://github.com/Adenialzz/SongUtils
Author: robin
Author-email: robin.seu@foxmail.com
License: MIT Licence
Keywords: pip,SongUtils
Platform: any
Requires-Dist: numpy
Requires-Dist: pillow
Dynamic: author
Dynamic: author-email
Dynamic: description
Dynamic: home-page
Dynamic: keywords
Dynamic: license
Dynamic: platform
Dynamic: requires-dist
Dynamic: summary
